[
    {
        "h1": "CrossFit",
        "intensity": ["<i class='fa-solid fa-dumbbell'></i>", 3]
    },
    {
        "h1": "Cardio",
        "intensity": ["<i class='fa-solid fa-dumbbell'></i>", 4]
    },
    {
        "h1": "AeroHit",
        "intensity": ["<i class='fa-solid fa-dumbbell'></i>", 3]
    },
    {
        "h1": "Musculação",
        "intensity": ["<i class='fa-solid fa-dumbbell'></i>", 5]
    },
    {
        "h1": "Aeróbica",
        "intensity": ["<i class='fa-solid fa-dumbbell'></i>", 3]
    }
]